wfx/__init__.py
wfx/__main__.py
wfx/constants.py
wfx/py.typed
wfx/settings.py
wfx/type_extraction.py
wfx/_assets/component_index.json
wfx/base/__init__.py
wfx/base/constants.py
wfx/base/agents/__init__.py
wfx/base/agents/agent.py
wfx/base/agents/callback.py
wfx/base/agents/context.py
wfx/base/agents/default_prompts.py
wfx/base/agents/errors.py
wfx/base/agents/events.py
wfx/base/agents/utils.py
wfx/base/agents/crewai/__init__.py
wfx/base/agents/crewai/crew.py
wfx/base/agents/crewai/tasks.py
wfx/base/astra_assistants/__init__.py
wfx/base/astra_assistants/util.py
wfx/base/chains/__init__.py
wfx/base/chains/model.py
wfx/base/composio/__init__.py
wfx/base/composio/composio_base.py
wfx/base/compressors/__init__.py
wfx/base/compressors/model.py
wfx/base/curl/__init__.py
wfx/base/curl/parse.py
wfx/base/data/__init__.py
wfx/base/data/base_file.py
wfx/base/data/docling_utils.py
wfx/base/data/utils.py
wfx/base/document_transformers/__init__.py
wfx/base/document_transformers/model.py
wfx/base/embeddings/__init__.py
wfx/base/embeddings/aiml_embeddings.py
wfx/base/embeddings/model.py
wfx/base/flow_processing/__init__.py
wfx/base/flow_processing/utils.py
wfx/base/huggingface/__init__.py
wfx/base/huggingface/model_bridge.py
wfx/base/io/__init__.py
wfx/base/io/chat.py
wfx/base/io/text.py
wfx/base/knowledge_bases/__init__.py
wfx/base/knowledge_bases/knowledge_base_utils.py
wfx/base/langchain_utilities/__init__.py
wfx/base/langchain_utilities/model.py
wfx/base/langchain_utilities/spider_constants.py
wfx/base/langwatch/__init__.py
wfx/base/langwatch/utils.py
wfx/base/mcp/__init__.py
wfx/base/mcp/constants.py
wfx/base/mcp/util.py
wfx/base/memory/__init__.py
wfx/base/memory/memory.py
wfx/base/memory/model.py
wfx/base/models/__init__.py
wfx/base/models/aiml_constants.py
wfx/base/models/anthropic_constants.py
wfx/base/models/aws_constants.py
wfx/base/models/chat_result.py
wfx/base/models/cometapi_constants.py
wfx/base/models/google_generative_ai_constants.py
wfx-0.1.13.dist-info/METADATA
wfx-0.1.13.dist-info/WHEEL
wfx-0.1.13.dist-info/entry_points.txt
wfx-0.1.13.dist-info/RECORD
