Metadata-Version: 2.4
Name: wfx
Version: 0.1.13
Summary: Aiexec Executor - A lightweight CLI tool for executing and serving Aiexec AI flows
Author-email: Gabriel Luiz Freitas Almeida <gabriel@aiexec.khulnasoft.com>
Requires-Python: <3.14,>=3.10
Requires-Dist: aiofile<4.0.0,>=3.8.0
Requires-Dist: aiofiles<25.0.0,>=24.1.0
Requires-Dist: asyncer<1.0.0,>=0.0.8
Requires-Dist: cachetools<6.0.0,>=5.5.2
Requires-Dist: chardet<6.0.0,>=5.2.0
Requires-Dist: defusedxml<1.0.0,>=0.7.1
Requires-Dist: docstring-parser<1.0.0,>=0.16
Requires-Dist: emoji<3.0.0,>=2.14.1
Requires-Dist: fastapi<1.0.0,>=0.115.13
Requires-Dist: httpx[http2]<1.0.0,>=0.24.0
Requires-Dist: json-repair<1.0.0,>=0.30.3
Requires-Dist: langchain-core<1.0.0,>=0.3.66
Requires-Dist: langchain~=0.3.23
Requires-Dist: loguru<1.0.0,>=0.7.3
Requires-Dist: nanoid<3.0.0,>=2.0.0
Requires-Dist: networkx<4.0.0,>=3.4.2
Requires-Dist: orjson<4.0.0,>=3.10.15
Requires-Dist: pandas<3.0.0,>=2.0.0
Requires-Dist: passlib<2.0.0,>=1.7.4
Requires-Dist: pillow<13.0.0,>=10.0.0
Requires-Dist: platformdirs<5.0.0,>=4.3.8
Requires-Dist: pydantic-settings<3.0.0,>=2.10.1
Requires-Dist: pydantic<3.0.0,>=2.0.0
Requires-Dist: python-dotenv<2.0.0,>=1.0.0
Requires-Dist: rich<14.0.0,>=13.0.0
Requires-Dist: structlog<26.0.0,>=25.4.0
Requires-Dist: tomli<3.0.0,>=2.2.1
Requires-Dist: typer<1.0.0,>=0.16.0
Requires-Dist: typing-extensions<5.0.0,>=4.14.0
Requires-Dist: uvicorn<1.0.0,>=0.34.3
Requires-Dist: validators<1.0.0,>=0.34.0
